wrld.py
wrld-1.1.dist-info/DESCRIPTION.rst
wrld-1.1.dist-info/METADATA
wrld-1.1.dist-info/RECORD
wrld-1.1.dist-info/WHEEL
wrld-1.1.dist-info/entry_points.txt
wrld-1.1.dist-info/metadata.json
wrld-1.1.dist-info/top_level.txt
