Metadata-Version: 2.0
Name: wrld
Version: 1.1
Summary: simplified bash loops (or, xargs -I on steroids)
Home-page: https://github.com/ninjaaron/wrld
Author: Aaron Christianson
Author-email: ninjaaron@gmail.com
License: BSD
Keywords: evaluate
Platform: UNKNOWN
